<document>
    <id>250486</id>
    <drucksachetyp>Kleine Anfrage</drucksachetyp>
    <dokumentart>Drucksache</dokumentart>
    <autoren_anzahl>46</autoren_anzahl>
    <typ>Dokument</typ>
    <vorgangsbezug_anzahl>1</vorgangsbezug_anzahl>
    <dokumentnummer>19/26765</dokumentnummer>
    <wahlperiode>19</wahlperiode>
    <herausgeber>BT</herausgeber>
    <pdf_hash>2fbf6a47f42684cc61f046a01f0d3636</pdf_hash>
    <aktualisiert>2022-07-26T19:57:15+02:00</aktualisiert>
    <vorgangsbezug>
      <id>273904</id>
      <titel>Aktueller Stand gemeldeter Insolvenzen und Ma&#223;nahmen der Bundesregierung</titel>
      <vorgangstyp>Kleine Anfrage</vorgangstyp>
    </vorgangsbezug>
    <urheber>
      <einbringer>false</einbringer>
      <bezeichnung>FDP</bezeichnung>
      <titel>Fraktion der FDP</titel>
    </urheber>
    <fundstelle>
      <pdf_url>https://dserver.bundestag.de/btd/19/267/1926765.pdf</pdf_url>
      <id>250486</id>
      <dokumentnummer>19/26765</dokumentnummer>
      <datum>2021-02-17</datum>
      <verteildatum>2021-02-19</verteildatum>
      <dokumentart>Drucksache</dokumentart>
      <drucksachetyp>Kleine Anfrage</drucksachetyp>
      <herausgeber>BT</herausgeber>
      <urheber>Fraktion der FDP</urheber>
    </fundstelle>
    <autoren_anzeige>
      <id>2020</id>
      <titel>Roman M&#252;ller-B&#246;hm, MdB, FDP</titel>
      <autor_titel>Roman M&#252;ller-B&#246;hm</autor_titel>
    </autoren_anzeige>
    <autoren_anzeige>
      <id>7549</id>
      <titel>Michael Theurer, MdB, FDP</titel>
      <autor_titel>Michael Theurer</autor_titel>
    </autoren_anzeige>
    <text>[Kleine Anfrage
der Abgeordneten Roman M&#252;ller-B&#246;hm, Michael Theurer, Reinhard Houben, 
Dr. Marcel Klinge, Dr. Martin Neumann, Manfred Todtenhausen, Gerald Ullrich, 
Sandra Weeser, Grigorios Aggelidis, Renata Alt, Christine Aschenberg-Dugnus, 
Nicole Bauer, Jens Beeck, Dr. Jens Brandenburg (Rhein-Neckar), Dr. Marco 
Buschmann, Carl-Julius Cronenberg, Dr. Marcus Faber, Daniel F&#246;st, Otto Fricke, 
Thomas Hacker, Reginald Hanke, Peter Heidt, Katrin Helling-Plahr, Markus 
Herbrand, Torsten Herbst, Katja Hessel, Ulla Ihnen, Olaf in der Beek, Pascal 
Kober, Carina Konrad, Konstantin Kuhle, Ulrich Lechte, Michael Georg Link, Till 
Mansmann, Dr. J&#252;rgen Martens, Alexander M&#252;ller, Dr. Wieland Schinnenburg, 
Matthias Seestern-Pauly, Judith Skudelny, Dr. Hermann Otto Solms, Dr. Marie-
Agnes Strack-Zimmermann, Benjamin Strasser, Katja Suding, Linda Teuteberg, 
Stephan Thomae, Nicole Westig und der Fraktion der FDP
Aktueller Stand gemeldeter Insolvenzen und Ma&#223;nahmen der Bundesregierung
Am 27. Januar 2020 wurde in Deutschland die erste Infektion mit COVID-19 
nachgewiesen. Seitdem stellt die Corona-Pandemie die Gesellschaft und
insbesondere die Unternehmen vor eine besondere Herausforderung. Neben dem
abnehmenden Konsum und der ausbleibenden Kundschaft stellt auch die
Umsetzung der Hygienema&#223;nahmen eine erhebliche Belastung dar, die zum Teil zu 
existenzbedrohenden Situationen f&#252;hrt. Ebenso tr&#228;gt der vorweihnachtlich
begonnene Lockdown und somit die Schlie&#223;ung des Einzelhandels zu einer
m&#246;glichen Insolvenzwelle bei. Zuvor schwer erarbeitete Gewinne der Unternehmen 
schmelzen tagt&#228;glich dahin und ein &#220;berleben ist zum Teil nur noch aufgrund 
einer immensen finanziellen Unterst&#252;tzung m&#246;glich. Auch die Medien
berichten von katastrophalen Zust&#228;nden und einer drohenden Insolvenzwelle
bundesweit in nahezu jeder Branche (https://www.tagesschau.de/wirtschaft/corona-ins
olvenzen-103.html). Zwar haben sowohl die Bundesregierung als auch einige 
Landesregierungen Ma&#223;nahmen ergriffen, um die Auswirkungen der Corona-
Pandemie zu reduzieren oder g&#228;nzlich zu verhindern, beispielsweise durch eine 
Aussetzung der Insolvenzantragspflicht sowie durch diverse monet&#228;re
&#220;berbr&#252;ckungskredite, jedoch wird nach Ansicht der Fragesteller allm&#228;hlich deutlich, 
dass diese Ma&#223;nahmen das Problem der drohenden Insolvenzen nicht
verhindert, sondern lediglich vertagt. Gerade Branchen, wie etwa die Schausteller
sowie die Tourismus- und Reisewirtschaft sind von dieser Entwicklung in
besonderer Weise betroffen und hoffen auf eine nachhaltige L&#246;sung, um eine
Pleitewelle abwenden zu k&#246;nnen.
Deutscher Bundestag Drucksache 19/26765
19. Wahlperiode 17.02.2021
Wir fragen die Bundesregierung:
&#8199;1. Wie viele Insolvenzen sind der Bundesregierung seit dem 27. Januar 2020 
bekannt geworden (bitte diese nach Kalenderwochen aufschl&#252;sseln)?
a) Wie viele dieser Insolvenzen sind nach Kenntnis der Bundesregierung 
auf den SARS-Cov-2-Virus und die damit verbundene Pandemie
zur&#252;ckzuf&#252;hren?
b) Wie viele Mitarbeiter sind nach Kenntnis der Bundesregierung von
diesen Insolvenzen je Kalenderwoche direkt betroffen?
c) Wie viele Mitarbeiter sind nach Kenntnis der Bundesregierung von
diesen Insolvenzen je Kalenderwoche indirekt betroffen?
d) Welche Branche ist nach Kenntnis der Bundesregierung seit dem 
27. Januar 2020 zahlenm&#228;&#223;ig am st&#228;rksten von Insolvenzen betroffen?
e) Welches Bundesland ist nach Kenntnis der Bundesregierung seit dem 
27. Januar 2020 zahlenm&#228;&#223;ig am st&#228;rksten von Insolvenzen betroffen?
&#8199;2. Wie viele Insolvenzantr&#228;ge sind nach Ansicht der Bundesregierung durch 
Ma&#223;nahmen der Bundesregierung seit dem 27. Januar 2020 verhindert 
worden, und durch welche konkreten Ma&#223;nahmen konnte dies geschehen?
a) Welche Ma&#223;nahmen zur Abwendung von Insolvenzen sind gescheitert?
b) Welche Ma&#223;nahmen zur Abwendung von Insolvenzen sind erfolgreich 
angewendet worden, und wie sahen diese konkret aus?
&#8199;3. Welche Ma&#223;nahmen hat die Bundesregierung seit dem 27. Januar 2020
ergriffen, um eine Abwendung von Insolvenzen aufgrund der Corona-
Pandemie zu verhindern (bitte den konkreten Zeitpunkt des Inkrafttretens 
der Ma&#223;nahme benennen)?
&#8199;4. Wie viele Insolvenzantr&#228;ge erwartet die Bundesregierung bis zum Ende 
des ersten Quartals 2021 aufgrund der Corona-Pandemie?
a) Ist die Bundesregierung der Ansicht, dass eine Insolvenzwelle droht, 
und wenn ja, inwiefern?
b) Wie wird sich nach Ansicht der Bundesregierung die Anzahl der
Insolvenzantr&#228;ge auf die Kalenderwochen bis zum Ende des ersten Quartals 
2021 entwickeln?
c) Welche Branche wird nach Ansicht der Bundesregierung von diesen 
Insolvenzantr&#228;gen am st&#228;rksten betroffen sein?
d) Zu welchem Zeitpunkt erwartet die Bundesregierung den
zahlenm&#228;&#223;igen H&#246;hepunkt der Insolvenzantr&#228;ge (bitte den konkreten Monat
benennen)?
&#8199;5. Wie wird sich nach Ansicht der Bundesregierung die Anzahl der
Arbeitslosen in der Bundesrepublik Deutschland bis zum Ende des ersten Quartals 
2021 entwickeln (bitte nach Monaten aufschl&#252;sseln)?
&#8199;6. Welche Ma&#223;nahmen plant die Bundesregierung f&#252;r die durch SARS-
CoV-2 bedingten Ver&#228;nderungen auf dem Arbeitsmarkt bez&#252;glich der
Insolvenzen in der Tourismusbranche, insbesondere hinsichtlich steigender 
Arbeitslosenzahlen in dieser Branche?
&#8199;7. Welche Gefahren sieht die Bundesregierung aufgrund der gemeldeten
Insolvenzen f&#252;r die Bundesrepublik Deutschland?
&#8199;8. Hat sich nach Ansicht der Bundesregierung die geplante Wirkung von 
Ma&#223;nahmen des Bundes gegen drohende Insolvenzen erf&#252;llt?
a) Falls ja, wie beurteilt die Bundesregierung die Nachhaltigkeit dieser 
Ma&#223;nahmen?
b) Falls nein, welche Probleme sieht die Bundesregierung, und welche 
Verbesserungen sollten aus Sicht der Bundesregierung vorgenommen 
werden?
c) Teilt die Bundesregierung die Ansicht der Fragesteller, dass die
Aussetzung der Insolvenzantragspflicht die Anzahl der Insolvenzen nicht
reduziert, sondern lediglich den Zeitpunkt von diesen verschoben hat, 
und wenn ja, inwiefern, und wenn nein, warum nicht?
&#8199;9. Hat sich die Bundesregierung mit den L&#228;ndern bei den Ma&#223;nahmen zur 
Abwendung drohender Insolvenzen abgestimmt oder in sonstiger Weise 
koordiniert, und wenn ja, inwiefern?
a) Wenn ja, welche Ma&#223;nahmen der L&#228;nder erwiesen sich nach Kenntnis 
der Bundesregierung f&#252;r besonders geeignet, um drohende Insolvenzen 
aufgrund der Corona-Pandemie zu verhindern?
b) Wenn ja, welche Ma&#223;nahmen der L&#228;nder erwiesen sich nach Kenntnis 
der Bundesregierung f&#252;r ungeeignet?
10. Wie hoch wird nach Ansicht der Bundesregierung der volkswirtschaftliche 
Schaden durch die Corona-Pandemie und der dadurch resultierenden
Insolvenzen f&#252;r die Bundesrepublik Deutschland bis zum Ende des ersten 
Quartals 2021 sein?
a) Inwiefern erwartet die Bundesregierung f&#252;r dieses Jahr (2021) eine 
&#228;hnliche Entwicklung wie im Jahr 2020?
b) Welche Berechnungsmodelle stehen der Bundesregierung zu diesem 
Zweck zur Verf&#252;gung?
11. Inwiefern kann abgesch&#228;tzt werden, wie viele Insolvenzen gemeldet
werden, sofern die Aussetzung der coronabedingten Insolvenzmeldungen 
nicht mehr besteht?
Berlin, den 27. Januar 2021
Christian Lindner und Fraktion
Gesamtherstellung: H. Heenemann GmbH &amp; Co. KG, Buch- und Offsetdruckerei, Bessemerstra&#223;e 83&#8211;91, 12103 Berlin, www.heenemann-druck.de
Vertrieb: Bundesanzeiger Verlag GmbH, Postfach 10 05 34, 50445 K&#246;ln, Telefon (02 21) 97 66 83 40, Fax (02 21) 97 66 83 44, www.betrifft-gesetze.de
ISSN 0722-8333]</text>
    <titel>Aktueller Stand gemeldeter Insolvenzen und Ma&#223;nahmen der Bundesregierung</titel>
    <datum>2021-02-17</datum>
  </document>
  