<document>
    <id>225100</id>
    <drucksachetyp>Antwort</drucksachetyp>
    <dokumentart>Drucksache</dokumentart>
    <autoren_anzahl>0</autoren_anzahl>
    <typ>Dokument</typ>
    <vorgangsbezug_anzahl>1</vorgangsbezug_anzahl>
    <dokumentnummer>19/6673</dokumentnummer>
    <wahlperiode>19</wahlperiode>
    <herausgeber>BT</herausgeber>
    <pdf_hash>9a87b8743635ef3bfe384bc32c5e6123</pdf_hash>
    <aktualisiert>2022-07-26T19:57:18+02:00</aktualisiert>
    <vorgangsbezug>
      <id>242253</id>
      <titel>Einf&#252;hrung von Online-Verfahren in die Zivilprozessordnung</titel>
      <vorgangstyp>Kleine Anfrage</vorgangstyp>
    </vorgangsbezug>
    <urheber>
      <einbringer>false</einbringer>
      <bezeichnung>BRg</bezeichnung>
      <titel>Bundesregierung</titel>
    </urheber>
    <ressort>
      <federfuehrend>true</federfuehrend>
      <titel>Bundesministerium der Justiz und f&#252;r Verbraucherschutz</titel>
    </ressort>
    <fundstelle>
      <pdf_url>https://dserver.bundestag.de/btd/19/066/1906673.pdf</pdf_url>
      <id>225100</id>
      <dokumentnummer>19/6673</dokumentnummer>
      <datum>2018-12-20</datum>
      <dokumentart>Drucksache</dokumentart>
      <drucksachetyp>Antwort</drucksachetyp>
      <herausgeber>BT</herausgeber>
      <urheber>Bundesregierung</urheber>
    </fundstelle>
    <text>[Die Antwort wurde namens der Bundesregierung mit Schreiben des Bundesministeriums der Justiz und f&#252;r
Verbraucherschutz vom 19. Dezember 2018 &#252;bermittelt. 
Die Drucksache enth&#228;lt zus&#228;tzlich &#8211; in kleinerer Schrifttype &#8211; den Fragetext. 
Deutscher Bundestag  Drucksache 19/6673 
19. Wahlperiode 20.12.2018 
Antwort 
der Bundesregierung 
auf die Kleine Anfrage der Abgeordneten Katrin Helling-Plahr, Stephan Thomae, 
Renata Alt, weiterer Abgeordneter und der Fraktion der FDP 
&#8211; Drucksache 19/6291 &#8211; 
Einf&#252;hrung von Online-Verfahren in die Zivilprozessordnung 
V o r b e m e r k u n g  d e r  F r a g e s t e l l e r  
Streitigkeiten, deren Streitwert 5 000 Euro nicht &#252;bersteigt, werden ausweislich 
&#167; 1 der Zivilprozessordnung (ZPO) i. V. m. &#167; 23 Nummer 1 des
Gerichtsverfassungsgesetzes (GVG) vor den Amtsgerichten verhandelt. Die
Fr&#252;hjahrskonferenz der Justizministerinnen und Justizminister der L&#228;nder hat beschlossen, die 
Verfahrensstruktur der Zivilklagen dahingehend zu untersuchen, ob
insbesondere f&#252;r den Bereich von geringf&#252;gigen Forderungen ein neues und
kosteng&#252;nstigeres Online-Verfahren entwickelt werden sollte. Dadurch soll effektiver 
Rechtsschutz auch im Bereich geringf&#252;giger Streitwerte gew&#228;hrt werden.
Online-Verfahren werden im Ausland bereits f&#252;r Streitigkeiten im geringf&#252;gigen 
Bereich genutzt. Das deutsche Verfahrensrecht sieht etwaige Regelungen bisher 
nicht vor und m&#252;sste ggf. durch den Bundesgesetzgeber ge&#228;ndert werden.
Ausweislich der ZP-Statistik (exemplarisch f&#252;r das Jahr 2017: www.destatis.de/ 
DE/Publikationen/Thematisch/Rechtspflege/GerichtePersonal/Zivilgerichte210 
0210177004.pdf?__blob=publicationFile) ist jedoch nicht ersichtlich, mit
welcher absoluten Anzahl von Verfahren die Gerichte im geringf&#252;gigen Bereich 
belastet sind. 
1. Hat die Bundesregierung Kenntnis davon, wie hoch die Eingangszahlen bei 
Gerichtsverfahren mit einem Streitwert unter 600 Euro sind (bitte nach
Bundesland und Oberlandesgerichtsbezirken in absoluten Zahlen f&#252;r die letzten 
f&#252;nf Jahre aufschl&#252;sseln)? 
2. Hat die Bundesregierung Kenntnis davon, wie hoch die Eingangszahlen bei 
Gerichtsverfahren mit einem Streitwert unter 2 000 Euro sind (bitte nach 
Bundesland und Oberlandesgerichtsbezirken in absoluten Zahlen f&#252;r die 
letzten f&#252;nf Jahre aufschl&#252;sseln)?
3. Hat die Bundesregierung Kenntnis davon, wie hoch die Eingangszahlen bei 
Gerichtsverfahren mit einem Streitwert unter 5 000 Euro sind (bitte nach 
Bundesland und Oberlandesgerichtsbezirken in absoluten Zahlen f&#252;r die 
letzten f&#252;nf Jahre aufschl&#252;sseln)? 
Die Fragen 1 bis 3 werden wegen ihres Sachzusammenhangs zusammen
beantwortet.  
In der vom Statistischen Bundesamt (Destatis) j&#228;hrlich ver&#246;ffentlichten
Justizstatistik (Fachserie 10 Reihe 2.1/Rechtspflege Zivilgerichte) werden jeweils
aufgeschl&#252;sselt nach verschiedenen Streitwertkategorien und den
Oberlandesgerichtsbezirken die erledigten Zivilverfahren vor den Amts-, Land- und
Oberlandesgerichten lediglich nach ihrem prozentualen Anteil an den
Gesamterledigungszahlen erfasst.  
Nach Streitwertkategorien aufgeschl&#252;sselte absolute Eingangszahlen enth&#228;lt die 
Justizstatistik nicht. 
4. Hat die Bundesregierung Kenntnis davon, wie hoch die Anzahl der Klagen 
vor den Amtsgerichten, die zu Protokoll der Gesch&#228;ftsstelle erhoben (&#167; 496 
ZPO a. E.) worden sind (bitte nach Bundesland und
Oberlandesgerichtsbezirken in absoluten Zahlen f&#252;r die letzten f&#252;nf Jahre aufschl&#252;sseln)? 
Wie hat sich dieser Anteil in den letzten zehn Jahren entwickelt? 
Der Bundesregierung ist die Anzahl der durch Erkl&#228;rung zu Protokoll der
Gesch&#228;ftsstelle erhobenen Klagen nicht bekannt. 
5. Ist die Bundesregierung der Auffassung, dass eine in der ZPO zu schaffende 
M&#246;glichkeit zur Klageerhebung mittels Online-Eingabemaske und darauf 
schnell folgender m&#252;ndlicher Verhandlung (&#8222;kleine L&#246;sung&#8220;) die
M&#246;glichkeiten effektiven Rechtsschutzes f&#252;r Naturalparteien hinsichtlich der damit 
einhergehenden Niederschwelligkeit erh&#246;hen w&#252;rde? 
Der Vorschlag f&#252;r ein sogenanntes online-Schnellverfahren, der auf einen
Vorsto&#223; des Landes Hamburg zur&#252;ckgeht, wird derzeit in der L&#228;nderarbeitsgruppe 
&#8222;Legal Tech&#8220; diskutiert. Die Arbeiten sind noch nicht abgeschlossen. Das
Bundesministerium der Justiz und f&#252;r Verbraucherschutz nimmt an den Sitzungen der 
Arbeitsgruppe teil. 
6. Hat die Bundesregierung Kenntnis davon, wie lange die durchschnittliche 
Verfahrensdauer in absoluten Werten in der Zivilgerichtsbarkeit ist (bitte 
nach Instanzen aufschl&#252;sseln)? 
7. Hat die Bundesregierung Kenntnis davon, wie lange die durchschnittliche 
Verfahrensdauer in absoluten Werten in der Zivilgerichtsbarkeit bei
Verfahren mit einem Streitwert unter 600 Euro ist? 
8. Hat die Bundesregierung Kenntnis davon, wie lange die durchschnittliche 
Verfahrensdauer in absoluten Werten in der Zivilgerichtsbarkeit bei
Verfahren mit einem Streitwert unter 2 000 Euro ist? 
9. Hat die Bundesregierung Kenntnis davon, wie lange die durchschnittliche 
Verfahrensdauer in absoluten Werten in der Zivilgerichtsbarkeit bei
Verfahren mit einem Streitwert unter 5 000 Euro ist? 
Die Fragen 6 bis 9 werden wegen ihres Sachzusammenhangs zusammen
beantwortet.
Im Jahr 2017 betrug nach der Justizstatistik die durchschnittliche
Verfahrensdauer f&#252;r erstinstanzliche Verfahren vor dem Amtsgericht 4,9 Monate, f&#252;r
erstinstanzliche Verfahren vor dem Landgericht 11,7 Monate, f&#252;r Berufungsverfahren 
vor dem Landgericht 5,7 Monate und f&#252;r Berufungsverfahren vor dem
Oberlandesgericht 6,7 Monate. Eine Aufschl&#252;sselung nach Streitwerten enth&#228;lt die
Justizstatistik nicht. Die durchschnittliche Verfahrensdauer f&#252;r die
Revisionsverfahren vor dem Bundesgerichtshof ist in der Justizstatistik ebenfalls nicht
ausgewiesen. 
10. Ist die Bundesregierung der Ansicht, dass die Verfahrensdauer Einfluss auf 
die Anzahl der Klageerhebungen hat? 
Der Bundesregierung liegen hierzu keine wissenschaftlichen Erkenntnisse vor. 
11. Hat die Bundesregierung Kenntnis davon, wie oft, seit Einf&#252;hrung des 
&#167; 128a ZPO im Jahr 2013, von der M&#246;glichkeit der Bild- und
Ton&#252;bertragung w&#228;hrend der m&#252;ndlichen Verhandlung Gebrauch gemacht wurde (bitte 
nach Bundesland und Oberlandesgerichtsbezirken aufschl&#252;sseln)? 
Der Bundesregierung liegen hierzu keine Statistiken vor. 
12. Ist die Bundesregierung der Auffassung, dass eine in der ZPO zu schaffende 
M&#246;glichkeit eines durchg&#228;ngigen Online-Verfahrens (Klageerhebung,
Einreichen der Schrifts&#228;tze wie Beweiserhebung digital, Wahrung des
M&#252;ndlichkeitsprinzips durch Videokonferenz &#8211; &#8222;gro&#223;e L&#246;sung&#8220;) geeignet w&#228;re, 
die durchschnittliche Verfahrensdauer zu verk&#252;rzen? 
Auf die Antwort zu Frage 5 wird verwiesen. 
13. Ist die Bundesregierung der Auffassung, dass das Vertrauen der B&#252;rger in 
den Rechtsstaat durch den Eindruck gef&#228;hrdet ist, dass es vermeintlich keine 
schnelle Rechtsdurchsetzung von Verfahren mit einem geringf&#252;gigen
Streitwert vor deutschen Gerichten gibt? 
14. Ist die Bundesregierung der Ansicht, dass sich die L&#228;nge der
Verfahrensdauer negativ bei den B&#252;rgern hinsichtlich der Zufriedenheit mit der Justiz 
auswirkt? 
Die Fragen 13 und 14 werden wegen ihres Sachzusammenhangs zusammen
beantwortet.  
Die Bundesregierung hat keine eigenen wissenschaftlichen Erkenntnisse dar&#252;ber, 
wie sich bei den B&#252;rgerinnen und B&#252;rgern die L&#228;nge des Verfahrens auf das
Vertrauen in den Rechtsstaat und die Zufriedenheit mit der Justiz auswirkt.
Ausweislich des Roland Rechtsreports 2018 genie&#223;t das deutsche Rechtssystem in der 
Bev&#246;lkerung ein hohes Ma&#223; an Vertrauen. Das Vertrauen der Bev&#246;lkerung in  
das deutsche Rechtssystem ist danach seit Jahren relativ stabil (siehe www. 
roland-rechtsschutz.de/media/rechtsschutz/pdf/unternehmen_1/ROLAND_ 
Rechtsreport_2018.pdf, dort S. 11).
15. Zu welchem Anteil ist, nach Auffassung der Bundesregierung, der in den 
letzten Jahren zu beobachtende R&#252;ckgang der Eingangszahlen in der
Zivilgerichtsbarkeit auf die Implementierung au&#223;ergerichtlicher
Streitbeilegungsoptionen zur&#252;ckzuf&#252;hren? 
16. Auf welche anderen Ursachen f&#252;hrt die Bundesregierung diesen R&#252;ckgang 
zur&#252;ck? 
17. Besteht nach Auffassung der Bundesregierung ein Kausalzusammenhang 
zwischen dem R&#252;ckgang der Eingangszahlen in der Zivilgerichtsbarkeit und 
eines m&#246;glichen Vertrauensverlusts der B&#252;rger gegen&#252;ber dem Rechtsstaat? 
18. Begr&#252;&#223;t die Bundesregierung den R&#252;ckgang der Eingangszahlen in der
Zivilgerichtsbarkeit? 
Die Fragen 15 bis 18 werden wegen ihres Sachzusammenhangs zusammen
beantwortet.  
Das Bundesministerium der Justiz und f&#252;r Verbraucherschutz beobachtet die 
r&#252;ckl&#228;ufige Entwicklung der Eingangszahlen genau. Aufschluss &#252;ber die
Ursachen kann jedoch nur eine wissenschaftliche Untersuchung geben, wie sie das 
Bundesministerium der Justiz und f&#252;r Verbraucherschutz plant. 
19. Wie bewertet die Bundesregierung die Tatsache, dass sich immer mehr
private Streitbeilegungsangebote (bspw. PayPal-K&#228;ufer- und -
Verk&#228;uferschutz) entwickeln? 
20. Wie bewertet die Bundesregierung die Tatsache, dass private
Streitbeilegungsangebote sich nicht an den Wertungen der Rechtsordnung orientieren 
m&#252;ssen? 
21. Ist die Bundesregierung der Ansicht, dass private
Streitbeilegungseinrichtungen in Konkurrenz zu den staatlichen Gerichten treten? 
Die Fragen 19 bis 21 werden wegen ihres Sachzusammenhangs zusammen
beantwortet. 
Die Bundesregierung h&#228;lt eine fr&#252;hzeitige konsensuale Beilegung von Konflikten 
ohne Inanspruchnahme der staatlichen Justiz insgesamt f&#252;r eine sinnvolle
Alternative zur gerichtlichen Konfliktl&#246;sung. 
Die Bundesregierung begr&#252;&#223;t insbesondere die zunehmende Anerkennung und 
Etablierung von &#252;berwiegend privatrechtlich organisierten
Verbraucherschlichtungsstellen nach dem Verbraucherstreitbeilegungsgesetz (VSBG). Die
Verfahren vor diesen Stellen sind durch das VSBG gesetzlich geregelt, f&#252;r den
Verbraucher kosteng&#252;nstig und meist einfach zug&#228;nglich. Gleichzeitig wird die
Verj&#228;hrung etwaiger Anspr&#252;che gehemmt. Die Schlichtungsvorschl&#228;ge dieser Stellen 
sollen gem&#228;&#223; &#167; 19 Absatz 1 VSBG am geltenden Recht ausgerichtet sein, wobei 
insbesondere die zwingenden Verbraucherschutzgesetze beachtet werden sollen. 
Das Ergebnis des Verfahrens ist dabei f&#252;r den Verbraucher nie und f&#252;r den
Unternehmer nur in Einzelf&#228;llen verbindlich.  
Die Bundesregierung hat dar&#252;ber hinaus Kenntnis von der Etablierung weiterer 
privater Schlichtungsstellen sowie anderer privater Stellen, die Konfliktl&#246;sungen 
anbieten. Die Bundesregierung sieht es daher als Aufgabe an, das Verh&#228;ltnis
zwischen staatlicher Justiz und privater Streitbeilegung weiterhin st&#228;ndig zu
hinterfragen und zu justieren.
Sowohl der Schlichtungsvorschlag einer Verbraucherschlichtungsstelle als auch 
die Entscheidung oder Empfehlung einer anderen privaten Stelle versperren im 
Regelfall nicht den Weg zur staatlichen Gerichtsbarkeit und k&#246;nnen auf diese 
Weise am Ma&#223;stab des geltenden Rechts gerichtlich &#252;berpr&#252;ft werden. 
22. Erachtet die Bundesregierung es als sinnvoll, die ZPO derart zu &#228;ndern, dass 
ein Online-Verfahren eingef&#252;hrt werden k&#246;nnte? 
23. Welche Normen stehen, nach Auffassung der Bundesregierung, der
Einf&#252;hrung einer M&#246;glichkeit zur Klageerhebung mittels Online-Eingabemaske 
und darauf schnell folgender m&#252;ndlicher Verhandlung (&#8222;kleine L&#246;sung&#8220;) de 
lege lata entgegen? 
24. Welche Normen stehen, nach Auffassung der Bundesregierung, der
Einf&#252;hrung eines durchg&#228;ngigen Online-Verfahrens (Klageerhebung, Einreichen 
der Schrifts&#228;tze wie Beweiserhebung digital, Wahrung des
M&#252;ndlichkeitsprinzips durch Videokonferenz &#8211; &#8222;gro&#223;e L&#246;sung&#8220;) de lege lata entgegen? 
25. Arbeitet das Bundesministerium der Justiz und f&#252;r Verbraucherschutz in der 
Arbeitsgruppe &#8222;Legal Tech&#8220; unterst&#252;tzend, hinsichtlich des Beschlusses der 
89. Justizministerkonferenz, mit (vgl. Beschluss der 89. Konferenz der
Justizministerinnen und Justizminister, TOP I.4)? 
Die Fragen 22 bis 25 werden wegen ihres Sachzusammenhangs zusammen
beantwortet.  
Es wird insoweit auf die Antwort zu Frage 5 verwiesen. 
26. Hat die Bundesregierung Kenntnis dar&#252;ber, wie hoch die Anzahl der B&#252;rger 
ist, die rechtsschutzversichert sind? 
Laut Bundesanstalt f&#252;r Finanzdienstleistungsaufsicht gibt es bei den von ihr
beaufsichtigten Versicherungsunternehmen 24,2 Millionen
Rechtsschutzversicherungen (Stand: Ende 2017, im Inland abgeschlossenes Gesch&#228;ft). 
27. Werden nach Auffassung der Bundesregierung die M&#246;glichkeiten des
Internets und der Digitalisierung ausreichend im Gerichtsverfahren
ber&#252;cksichtigt? 
Die Bundesregierung hat es sich zur Aufgabe gemacht, die Digitalisierung im 
Rechtswesen nachdr&#252;cklich zu f&#246;rdern. Auf die Antwort der Bundesregierung zu 
Frage 1 der Kleinen Anfrage der Fraktion der FDP auf
Bundestagsdrucksache 19/5438 wird insoweit verwiesen. 
28. Wie bewertet die Bundesregierung die Einrichtung des Small Claims Court 
in Gro&#223;britannien, des Civil Resolution Tribunals in British Columbia
(Kanada) und des neuen Online-Prozessportals in D&#228;nemark? 
Die Bundesregierung verfolgt die rechts- und justizpolitischen Initiativen anderer 
L&#228;nder mit Interesse. Die weitere Entwicklung und die dort gemachten
Erfahrungen bleiben abzuwarten. 
29. Plant die Bundesregierung die Einf&#252;hrung eines Online-Verfahrens f&#252;r 
Rechtsstreitigkeiten mit geringf&#252;gigem Streitwert? 
Es wird auf die Antwort zu Frage 5 verwiesen. 
 
 
 
 
 
 
 
Satz: Satzweiss.com Print, Web, Software GmbH, Mainzer Stra&#223;e 116, 66121 Saarbr&#252;cken, www.satzweiss.com 
Druck: Printsystem GmbH, Schafw&#228;sche 1-3, 71296 Heimsheim, www.printsystem.de 
Vertrieb: Bundesanzeiger Verlag GmbH, Postfach 10 05 34, 50445 K&#246;ln, Telefon (02 21) 97 66 83 40, Fax (02 21) 97 66 83 44, www.betrifft-gesetze.de 
ISSN 0722-8333]</text>
    <titel>auf die Kleine Anfrage
- Drucksache 19/6291 -
Einf&#252;hrung von Online-Verfahren in die Zivilprozessordnung</titel>
    <datum>2018-12-20</datum>
  </document>
  